{
	"name": "Reservation",
	"version": "0.0.1",
	"author": [
		"Owen Kellie-Smith"
	],
	"url": "https://github.com/owen-kellie-smith/reservation/",
	"descriptionmsg": "reservation-desc",
	"license-name": "MIT",
	"type": "other",
	"AutoloadClasses": {
		"PEAR": "PEAR/PEAR.php",
		"HTML_Common2": "PEAR/HTML/Common2.php",
		"HTML_QuickForm2": "PEAR/HTML/QuickForm2.php",
		"HTML_QuickForm2_Container": "PEAR/HTML/QuickForm2/Container.php",
		"HTML_QuickForm2_Node": "PEAR/HTML/QuickForm2/Node.php",
		"HTML_QuickForm2_DataSource_SuperGlobal": "PEAR/HTML/QuickForm2/DataSource/SuperGlobal.php",
  		"HTML_Table_Storage": "PEAR/HTML/Table/Storage.php",
  		"HTML_Table": "PEAR/HTML/Table.php",
  		"HTML_Common": "PEAR/HTML/Common.php",
		"Validate": "PEAR/Validate.php",
		"SpecialReservation": "specials/SpecialReservation.php",
		"ReservationBooking":	"includes/ReservationBooking.php",
		"ReservationController":	"includes/ReservationController.php",
		"ReservationCollection": "includes/ReservationCollection.php",
		"ReservationDBInterface": "includes/ReservationDBInterface.php",
		"ReservationForm": "includes/ReservationForm.php",
		"ReservationHooks": "Reservation.hooks.php",
		"ReservationXML": "includes/ReservationXML.php",
		"ReservationFormXML": "includes/ReservationFormXML.php",
		"ReservationObject": "includes/ReservationObject.php",
		"ReservationRender": "includes/ReservationRender.php"
	},
	"ExtensionMessagesFiles": {
		"ReservationAlias": "Reservation.i18n.alias.php"
	},
	"Hooks": {
		"LoadExtensionSchemaUpdates": [
			"ReservationHooks::mySchemaUpdate"
		]
	},
	"MessagesDirs": {
		"Reservation": [
			"i18n"
		]
	},
	"ResourceFileModulePaths": {
		"localBasePath": "",
		"remoteExtPath": "Reservation"
	},
	"ResourceModules": {
		"ext.Reservation": {
			"styles": [
				"modules/ext.Reservation.css"
			]
		}
	},
	"SpecialPages": {
		"Reservation": "SpecialReservation"
	},
	"manifest_version": 1
}
